LICENSE
MANIFEST.in
README.rst
helga_jeopardy.py
setup.py
helga_jeopardy.egg-info/PKG-INFO
helga_jeopardy.egg-info/SOURCES.txt
helga_jeopardy.egg-info/dependency_links.txt
helga_jeopardy.egg-info/entry_points.txt
helga_jeopardy.egg-info/requires.txt
helga_jeopardy.egg-info/top_level.txt
helga_jeopardy.egg-info/zip-safe