Metadata-Version: 1.1
Name: helga-jeopardy
Version: 0.3.14
Summary: HALP
Home-page: UNKNOWN
Author: Justin Caratzas
Author-email: bigjust@lambdaphil.es
License: LICENSE
Keywords: irc bot jeopardy
Platform: UNKNOWN
Classifier: Development Status :: 4 - Beta
Classifier: License :: OSI Approved :: GNU General Public License v3 (GPLv3)
Classifier: Operating System :: OS Independent
Classifier: Programming Language :: Python
Classifier: Topic :: Software Development :: Libraries :: Python Modules
